ai_harness/__init__.py
ai_harness/buffer.py
ai_harness/configclasses.py
ai_harness/configuration.py
ai_harness/datautils.py
ai_harness/executors.py
ai_harness/fileutils.py
ai_harness/harnessutils.py
ai_harness/inspector.py
ai_harness/objectproxy.py
ai_harness/tqdmutils.py
ai_harness/xml2object.py
ai_harness/language/__init__.py
ai_harness/language/langconv.py
ai_harness/language/zh_wiki.py
ai_harness-0.4.32.dist-info/LICENSE.txt
ai_harness-0.4.32.dist-info/METADATA
ai_harness-0.4.32.dist-info/WHEEL
ai_harness-0.4.32.dist-info/top_level.txt
ai_harness-0.4.32.dist-info/RECORD
